libgravatar/__init__.py
libgravatar-1.0.2.dist-info/LICENSE
libgravatar-1.0.2.dist-info/METADATA
libgravatar-1.0.2.dist-info/WHEEL
libgravatar-1.0.2.dist-info/top_level.txt
libgravatar-1.0.2.dist-info/RECORD
