Metadata-Version: 2.1
Name: libgravatar
Version: 1.0.2
Summary: A library that provides a Python 3 interface for the Gravatar API.
Home-page: https://github.com/pabluk/libgravatar
Author: Pablo Seminario
Author-email: pablo@seminar.io
License: GNU General Public License v3 (GPLv3)
Project-URL: Bug Reports, https://github.com/pabluk/libgravatar/issues
Project-URL: Source, https://github.com/pabluk/libgravatar
Project-URL: Documentation, https://libgravatar.readthedocs.io
Keywords: gravatar
Platform: UNKNOWN
Classifier: Development Status :: 5 - Production/Stable
Classifier: Intended Audience :: Developers
Classifier: License :: OSI Approved :: GNU General Public License v3 (GPLv3)
Classifier: Operating System :: OS Independent
Classifier: Programming Language :: Python :: 2
Classifier: Programming Language :: Python :: 2.6
Classifier: Programming Language :: Python :: 2.7
Classifier: Programming Language :: Python :: 3
Classifier: Programming Language :: Python :: 3.6
Classifier: Programming Language :: Python :: 3.7
Classifier: Programming Language :: Python :: 3.8
Classifier: Programming Language :: Python :: 3.9
Classifier: Programming Language :: Python :: 3.10
Classifier: Programming Language :: Python :: 3.11
Classifier: Topic :: Software Development :: Libraries
License-File: LICENSE
